yaqd_pololu/VERSION
yaqd_pololu/__init__.py
yaqd_pololu/__version__.py
yaqd_pololu/_pololu_ticcmd.py
yaqd_pololu/pololu-ticcmd.avpr
yaqd_pololu/pololu-ticcmd.toml
yaqd_pololu-2025.4.0.dist-info/entry_points.txt
yaqd_pololu-2025.4.0.dist-info/licenses/LICENSE
yaqd_pololu-2025.4.0.dist-info/WHEEL
yaqd_pololu-2025.4.0.dist-info/METADATA
yaqd_pololu-2025.4.0.dist-info/RECORD
