Metadata-Version: 2.4
Name: yaqd-pololu
Version: 2025.4.0
Summary: Daemons for Pololu motor controllers.
Author: Dan Kohler
Maintainer: yaq developers
Requires-Python: >=3.7
Classifier: Development Status :: 2 - Pre-Alpha
Classifier: Intended Audience :: Science/Research
Classifier: License :: OSI Approved :: GNU Lesser General Public License v3 (LGPLv3)
Classifier: Natural Language :: English
Classifier: Programming Language :: Python :: 3
Classifier: Programming Language :: Python :: 3.10
Classifier: Programming Language :: Python :: 3.11
Classifier: Programming Language :: Python :: 3.12
Classifier: Topic :: Scientific/Engineering
License-File: LICENSE
Requires-Dist: yaqd-core>=2023.6.0
Requires-Dist: pyyaml
Project-URL: Homepage, https://yaq.fyi
Project-URL: Issues, https://github.com/yaq-project/yaqd-pololu/issues
Project-URL: Source, https://github.com/yaq-project/yaqd-pololu
